libcypher_parser/__init__.py
libcypher_parser/parser.c
libcypher_parser/parser.cpython-37m-darwin.so
libcypher_parser/parser.pxd
libcypher_parser/parser.pyx
libcypher_parser_python-0.0.5.dist-info/LICENSE
libcypher_parser_python-0.0.5.dist-info/METADATA
libcypher_parser_python-0.0.5.dist-info/WHEEL
libcypher_parser_python-0.0.5.dist-info/top_level.txt
libcypher_parser_python-0.0.5.dist-info/RECORD
