Metadata-Version: 2.1
Name: libcypher-parser-python
Version: 0.0.5
Summary: Python/Cython interface for libcypher-parser
Home-page: https://github.com/inonit/libcypher-parser-python
Author: Rolf Håvard Blindheim
Author-email: rhblind@gmail.com
License: Apache License 2.0
Download-URL: https://github.com/inonit/libcypher-parser-python.git
Platform: UNKNOWN
Classifier: Operating System :: OS Independent
Classifier: Development Status :: 4 - Beta
Classifier: Environment :: Plugins
Classifier: Intended Audience :: Developers
Classifier: License :: OSI Approved :: Apache Software License
Classifier: Programming Language :: Python :: 3
Classifier: Topic :: Software Development :: Libraries :: Python Modules
